bitbully_databases/__init__.py
bitbully_databases/bitbully_databases.py
bitbully_databases/assets/book_12ply.dat
bitbully_databases/assets/book_12ply_distances.dat
bitbully_databases/assets/book_8ply.dat
bitbully_databases-0.0.2.dist-info/licenses/LICENSE
bitbully_databases-0.0.2.dist-info/METADATA
bitbully_databases-0.0.2.dist-info/WHEEL
bitbully_databases-0.0.2.dist-info/top_level.txt
bitbully_databases-0.0.2.dist-info/RECORD
