Metadata-Version: 2.4
Name: bitbully-databases
Version: 0.0.2
Summary: Opening Databases for the Board Game Connect-4
Author: Markus Thill
Maintainer: Markus Thill
License-Expression: MIT
Project-URL: Homepage, https://github.com/MarkusThill/bitbully-databases
Project-URL: Issues, https://github.com/MarkusThill/bitbully-databases/issues
Keywords: connect-4,opening book,database
Classifier: Programming Language :: Python :: 3
Classifier: Programming Language :: Python :: 3 :: Only
Classifier: Programming Language :: Python :: 3.10
Classifier: Programming Language :: Python :: 3.11
Classifier: Programming Language :: Python :: 3.12
Classifier: Programming Language :: Python :: Implementation :: CPython
Requires-Python: >=3.10
License-File: LICENSE
Provides-Extra: dev
Requires-Dist: commitizen; extra == "dev"
Requires-Dist: pre-commit; extra == "dev"
Requires-Dist: build; extra == "dev"
Requires-Dist: twine; extra == "dev"
Requires-Dist: readme_renderer[md]; extra == "dev"
Requires-Dist: keyrings.alt; extra == "dev"
Requires-Dist: pydoclint; extra == "dev"
Requires-Dist: mkdocs; extra == "dev"
Requires-Dist: mkdocstrings[python]; extra == "dev"
Requires-Dist: mkdocs-material; extra == "dev"
Requires-Dist: pytest; extra == "dev"
Requires-Dist: pyrefly; extra == "dev"
Provides-Extra: notebooks
Requires-Dist: matplotlib; extra == "notebooks"
Requires-Dist: ipywidgets; extra == "notebooks"
Requires-Dist: ipympl; extra == "notebooks"
Requires-Dist: numpy; extra == "notebooks"
Provides-Extra: ci
Requires-Dist: pytest; extra == "ci"
Requires-Dist: ruff; extra == "ci"
Dynamic: license-file
